brynq_sdk_adp_decidium/__init__.py
brynq_sdk_adp_decidium/decidium.py
brynq_sdk_adp_decidium/dependents.py
brynq_sdk_adp_decidium/document.py
brynq_sdk_adp_decidium/pay_distributions.py
brynq_sdk_adp_decidium/payroll.py
brynq_sdk_adp_decidium/test_decidium.py
brynq_sdk_adp_decidium/work_assignment.py
brynq_sdk_adp_decidium/worker_normalization.py
brynq_sdk_adp_decidium/worker_update_functions.py
brynq_sdk_adp_decidium/workers.py
brynq_sdk_adp_decidium/schemas/__init__.py
brynq_sdk_adp_decidium/schemas/dependents.py
brynq_sdk_adp_decidium/schemas/document.py
brynq_sdk_adp_decidium/schemas/pay_distributions.py
brynq_sdk_adp_decidium/schemas/payroll.py
brynq_sdk_adp_decidium/schemas/work_assignment.py
brynq_sdk_adp_decidium/schemas/workers.py
brynq_sdk_adp_decidium-1.0.1.dev13.dist-info/METADATA
brynq_sdk_adp_decidium-1.0.1.dev13.dist-info/WHEEL
brynq_sdk_adp_decidium-1.0.1.dev13.dist-info/top_level.txt
brynq_sdk_adp_decidium-1.0.1.dev13.dist-info/RECORD
