Metadata-Version: 2.4
Name: brynq_sdk_adp_decidium
Version: 1.0.1.dev13
Summary: ADP Decidium wrapper from BrynQ
Author: BrynQ
Author-email: support@brynq.com
License: BrynQ License
Requires-Dist: brynq-sdk-brynq<5,>=4
Requires-Dist: pandas<3.0.0,>=2.2.0
Requires-Dist: pydantic<3.0.0,>=2.5.0
Requires-Dist: pandera<1.0.0,>=0.16.0
Requires-Dist: requests<3.0.0,>=2.25.1
Requires-Dist: brynq-sdk-functions>=2.0.5
Requires-Dist: tenacity==8.2.3
Dynamic: author
Dynamic: author-email
Dynamic: description
Dynamic: license
Dynamic: requires-dist
Dynamic: summary
